setup.py
pytlearn/__init__.py
pytlearn/convenience.py
pytlearn.egg-info/PKG-INFO
pytlearn.egg-info/SOURCES.txt
pytlearn.egg-info/dependency_links.txt
pytlearn.egg-info/top_level.txt