Metadata-Version: 1.1
Name: pytlearn
Version: 4.0.7
Summary: Python library to perform operations on highly structured data
Home-page: UNKNOWN
Author: MakersByte
Author-email: joshcahil@gmail.com
License: MIT
Platform: UNKNOWN
Classifier: Development Status :: 5 - Production/Stable
Classifier: Intended Audience :: Education
Classifier: Operating System :: OS Independent
Classifier: License :: OSI Approved :: MIT License
Classifier: Programming Language :: Python :: 3
